feast/feature_server.py
feast/data_format.py
feast/flags_helper.py
feast/stream_feature_view.py
feast/flags.py
feast/importer.py
feast/repo_contents.py
feast/driver_test_data.py
feast/wait.py
feast/feature_store.py
feast/transformation_server.py
feast/version.py
feast/feature_view_projection.py
feast/usage.py
feast/registry_store.py
feast/registry.py
feast/field.py
feast/data_source.py
feast/inference.py
feast/proto_json.py
feast/type_map.py
feast/types.py
feast/on_demand_feature_view.py
feast/constants.py
feast/names.py
feast/feature.py
feast/value_type.py
feast/batch_feature_view.py
feast/request_feature_view.py
feast/errors.py
feast/repo_operations.py
feast/entity.py
feast/online_response.py
feast/saved_dataset.py
feast/feast_object.py
feast/base_feature_view.py
feast/cli.py
feast/utils.py
feast/repo_config.py
feast/__init__.py
feast/feature_view.py
feast/py.typed
feast/feature_service.py
feast/templates/README.md
feast/templates/postgres/test.py
feast/templates/postgres/bootstrap.py
feast/templates/postgres/feature_store.yaml
feast/templates/postgres/driver_repo.py
feast/templates/postgres/__init__.py
feast/templates/gcp/test.py
feast/templates/gcp/feature_store.yaml
feast/templates/gcp/driver_repo.py
feast/templates/gcp/__init__.py
feast/templates/snowflake/test.py
feast/templates/snowflake/bootstrap.py
feast/templates/snowflake/feature_store.yaml
feast/templates/snowflake/driver_repo.py
feast/templates/local/bootstrap.py
feast/templates/local/feature_store.yaml
feast/templates/local/__init__.py
feast/templates/local/example.py
feast/templates/minimal/feature_store.yaml
feast/templates/hbase/bootstrap.py
feast/templates/hbase/feature_store.yaml
feast/templates/hbase/__init__.py
feast/templates/hbase/example.py
feast/templates/aws/test.py
feast/templates/aws/bootstrap.py
feast/templates/aws/feature_store.yaml
feast/templates/aws/driver_repo.py
feast/templates/aws/__init__.py
elemeno_ai_feast-0.18.4.dist-info/entry_points.txt
elemeno_ai_feast-0.18.4.dist-info/WHEEL
elemeno_ai_feast-0.18.4.dist-info/top_level.txt
elemeno_ai_feast-0.18.4.dist-info/METADATA
elemeno_ai_feast-0.18.4.dist-info/RECORD
